cluster_moe/__init__.py
cluster_moe/main.py
cluster_moe-0.0.2.dist-info/LICENSE
cluster_moe-0.0.2.dist-info/METADATA
cluster_moe-0.0.2.dist-info/WHEEL
cluster_moe-0.0.2.dist-info/RECORD
